api/__init__.py
api/app.py
api/models/__init__.py
api/routes/__init__.py
api/routes/admin_routes.py
api/routes/basin_routes.py
api/routes/station_routes.py
core/__init__.py
core/calculation/__init__.py
core/calculation/data_validation.py
core/calculation/rainfall_avg.py
core/calculation/spatial_analysis.py
core/data_import/__init__.py
core/data_import/geopackage_import.py
core/data_import/station_import.py
core/gis_service/__init__.py
core/gis_service/admin_region_service.py
core/gis_service/basin_region_relation.py
core/gis_service/basin_station_relation.py
core/gis_service/region_station_relation.py
core/gis_service/shp_util.py
data/__init__.py
hydropostgis/__init__.py
hydropostgis/core/__init__.py
hydropostgis/core/gis_service/__init__.py
hydropostgis/core/gis_service/admin_region_service.py
hydropostgis/utils/__init__.py
hydropostgis/utils/cache_util.py
hydropostgis/utils/json_util.py
hydropostgis/utils/postgres_util.py
service/__init__.py
utils/__init__.py
utils/cache_util.py
utils/id_generator.py
utils/json_util.py
utils/postgres_util.py
utils/format_transform/__init__.py
utils/format_transform/geojson_to_gpkg.py
utils/minio/__init__.py
utils/minio/hres.py
utils/minio/minio_util_with_cert.py
hydropostgis-0.1.1.dist-info/METADATA
hydropostgis-0.1.1.dist-info/WHEEL
hydropostgis-0.1.1.dist-info/top_level.txt
hydropostgis-0.1.1.dist-info/RECORD
