Metadata-Version: 2.4
Name: hydropostgis
Version: 0.1.1
Summary: 水文地理信息服务平台
Home-page: https://gitcode.com/dlut-water/HydroPostGIS.git
Author: denghaozhe
Author-email: 22d2h2z@gmal.com
Classifier: Programming Language :: Python :: 3
Classifier: License :: OSI Approved :: MIT License
Classifier: Operating System :: OS Independent
Classifier: Intended Audience :: Science/Research
Classifier: Topic :: Scientific/Engineering :: GIS
Requires-Python: >=3.8
Requires-Dist: geopandas==1.0.1
Requires-Dist: Shapely==2.0.7
Requires-Dist: pandas==2.2.3
Requires-Dist: psycopg2==2.9.9
Requires-Dist: SQLAlchemy==2.0.40
Requires-Dist: loguru==0.7.2
Requires-Dist: python-dotenv==1.1.0
Requires-Dist: Requests==2.32.3
Requires-Dist: urllib3==2.3.0
Dynamic: author
Dynamic: author-email
Dynamic: classifier
Dynamic: description
Dynamic: description-content-type
Dynamic: home-page
Dynamic: requires-dist
Dynamic: requires-python
Dynamic: summary
